[
    {
        "nome_evento": "rock in rio",
        "valor": 70.0,
        "descricao": "Id nostrud ea aliquip quis pariatur ad consectetur sunt aliquip Lorem.",
        "quantIngressos": 73
    },
    {
        "nome_evento": "lollapalooza",
        "valor": 100.0,
        "descricao": "Incididunt culpa est reprehenderit nisi occaecat consequat.",
        "quantIngressos": 50
    },
    {
        "nome_evento": "coachella",
        "valor": 150.0,
        "descricao": "Proident occaecat reprehenderit labore est laborum pariatur sint.",
        "quantIngressos": 13
    }
]